HCPInterface/__init__.py
HCPInterface/cli/__init__.py
HCPInterface/cli/base.py
HCPInterface/cli/functions.py
HCPInterface/cli/hci_functions.py
HCPInterface/hci/__init__.py
HCPInterface/hci/hci.py
HCPInterface/hcp/__init__.py
HCPInterface/hcp/config.py
HCPInterface/hcp/errors.py
HCPInterface/hcp/hcp.py
HCPInterface/hcp/helpers.py
HCPInterface/preproc/__init__.py
HCPInterface/preproc/preproc.py
HCPInterface-2.3.4.data/data/HCPInterface/config.ini
HCPInterface-2.3.4.data/data/reference/covidMetadataAllowedValues.csv
HCPInterface-2.3.4.data/data/reference/covidMetadataTemplate.csv
HCPInterface-2.3.4.data/data/testdata/test.json
HCPInterface-2.3.4.data/data/testdata/test_reads_R1.fasterq
HCPInterface-2.3.4.data/data/testdata/test_reads_R1.fastq.gz
tests/__init__.py
tests/simpleConnectionTest.py
tests/test_cmds.py
tests/test_hcp.py
tests/data/test.json
tests/data/test_reads_R1.fasterq
tests/data/test_reads_R1.fastq.gz
HCPInterface-2.3.4.dist-info/LICENSE
HCPInterface-2.3.4.dist-info/METADATA
HCPInterface-2.3.4.dist-info/WHEEL
HCPInterface-2.3.4.dist-info/entry_points.txt
HCPInterface-2.3.4.dist-info/top_level.txt
HCPInterface-2.3.4.dist-info/RECORD
