Metadata-Version: 2.1
Name: HCPInterface
Version: 2.3.4
Summary: UNKNOWN
Home-page: https://github.com/genomic-medicine-sweden/HCPInterface
Author: Isak Sylvin
Author-email: isak.sylvin@gu.se
License: UNKNOWN
Project-URL: Bug Tracker, https://github.com/genomic-medicine-sweden/HCPInterface/issues
Platform: UNKNOWN
Classifier: Programming Language :: Python :: 3
Classifier: License :: OSI Approved :: GNU General Public License v2 (GPLv2)
Classifier: Operating System :: OS Independent
Requires-Python: >=3.6
License-File: LICENSE
Requires-Dist: boto3 (==1.12.34)
Requires-Dist: click (==7.1.2)
Requires-Dist: requests (==2.25.0)
